README.rst
setup.py
sticks/__init__.py
sticks/sticks.py
sticks.egg-info/PKG-INFO
sticks.egg-info/SOURCES.txt
sticks.egg-info/dependency_links.txt
sticks.egg-info/entry_points.txt
sticks.egg-info/namespace_packages.txt
sticks.egg-info/top_level.txt