Metadata-Version: 1.0
Name: sticks
Version: 0.0.12
Summary: Simple game application.
Home-page: https://github.com/ganeshhubale/game_of_sticks
Author: ganeshhubale.
Author-email: ganeshhubale03@gmail.com
License: MIT
Platform: UNKNOWN
